<?xml version="1.0"?>
<doctrine-mapping xmlns="http://doctrine-project.org/schemas/orm/doctrine-mapping" xsi="http://www.w3.org/2001/XMLSchema-instance" schemaLocation="http://doctrine-project.org/schemas/orm/doctrine-mapping.xsd">
  <entity name="Db\Entity\Venue">
    <id name="id" type="integer"/>
    <field name="name" type="string" nullable="false"/>
    <field name="note" type="text" nullable="true"/>
    <field name="zipcode" type="string" nullable="true"/>
    <many-to-one field="city" target-entity="Db\Entity\City" inversed-by="venues">
      <join-columns>
        <join-column name="City_id" referenced-column-name="id" nullable="false"/>
      </join-columns>
    </many-to-one>
    <one-to-many field="shows" target-entity="Db\Entity\Show" mapped-by="venue"/>
    <one-to-many field="links" target-entity="Db\Entity\VenueLink" mapped-by="venue"/>
    <many-to-many field="venueGroups" target-entity="Db\Entity\VenueGroup" inversed-by="venues">
      <join-table name="VenueGroupVenue">
        <join-columns>
          <join-column name="Venue_id" referenced-column-name="id" nullable="false"/>
        </join-columns>
        <inverse-join-columns>
          <join-column name="VenueGroup_id" referenced-column-name="id" nullable="false"/>
        </inverse-join-columns>
      </join-table>
    </many-to-many>
  </entity>
</doctrine-mapping>
